mkdocs_yaml_schema_plugin
